src/dram_ori.v
module dram_ori (
  // inputs
  input clk,
  input ren,
  input wen,
  input [18:0] raddr,
  input [18:0] waddr,
  input [7:0] wdata,
  input writefile,  // comment out later
  
  // outputs
  output reg [7:0] rdata
);

parameter D_WIDTH =  8;
parameter A_WIDTH =  19;
parameter A_DEPTH = (1 << A_WIDTH);

integer i;
reg [D_WIDTH - 1:0] memory [0:A_DEPTH - 1];

integer out;

always @(posedge clk) begin
  if (ren)
    rdata <= memory[raddr];
  if (wen)
    memory[waddr] <= wdata;
end

// comment out this block later
always @(posedge writefile) begin
  out = $fopen("out.txt","w");
  for (i=0; i<307200; i=i+1)
    $fwrite(out,"%h\n",memory[i]);
  $fclose(out);
end

initial
begin
  for(i = 0; i < A_DEPTH; i = i + 1)
    memory[i] = 0;
  $readmemh("../../figures/bf/img1.txt", memory, 0, 307199);
  end

endmodule

test/dram_ori_tb.v
`timescale 1 ns/ 1 ps
module dram_ori_tb();
reg clk, ren, wen;
reg [18:0] raddr;
reg [18:0] waddr;
reg [7:0] wdata;
wire [7:0] rdata;
reg writefile;

dram_ori dr(clk, ren, wen, raddr, waddr, wdata, writefile, rdata);

initial begin
	clk = 1'b0;
	repeat (1000) clk = #5 ~clk;
end

initial
  begin
    $dumpfile("dram_ori_tb.vcd");
    $dumpvars(0, dram_ori_tb);
    #20
    // test 1
    ren = 1'b1;
    wen = 1'b0;
    raddr = 20'b0;
    waddr = 20'b0;
    wdata = 8'b0;
    writefile = 1'b0;
    #10
    // test 2
    ren = 1'b1;
    wen = 1'b0;
    raddr = 20'b1;
    waddr = 20'b0;
    wdata = 8'b0;
    #10
    // test 3
    ren = 1'b1;
    wen = 1'b0;
    raddr = 20'b10;
    waddr = 20'b0;
    wdata = 8'b0;
    #10
    // test 4
    ren = 1'b1;
    wen = 1'b0;
    raddr = 20'b1001010111111111110;
    waddr = 20'b0;
    wdata = 8'b0;
    #10
    // test 5
    ren = 1'b1;
    wen = 1'b0;
    raddr = 20'b1001010111111111111;
    waddr = 20'b0;
    wdata = 8'b0;
    #10
    
    writefile = 1'b1;
    #20
    $finish;
  end
  
endmodule

test/result/dram_ori_tb.vcd
$date
	Sun May 22 14:36:08 2022
$end
$version
	Icarus Verilog
$end
$timescale
	1ps
$end
$scope module dram_ori_tb $end
$var wire 8 ! rdata [7:0] $end
$var reg 1 " clk $end
$var reg 19 # raddr [18:0] $end
$var reg 1 $ ren $end
$var reg 19 % waddr [18:0] $end
$var reg 8 & wdata [7:0] $end
$var reg 1 ' wen $end
$var reg 1 ( writefile $end
$scope module dr $end
$var wire 1 " clk $end
$var wire 19 ) raddr [18:0] $end
$var wire 1 $ ren $end
$var wire 19 * waddr [18:0] $end
$var wire 8 + wdata [7:0] $end
$var wire 1 ' wen $end
$var wire 1 ( writefile $end
$var reg 8 , rdata [7:0] $end
$var integer 32 - i [31:0] $end
$var integer 32 . out [31:0] $end
$upscope $end
$upscope $end
$enddefinitions $end
#0
$dumpvars
bx .
b10000000000000000000 -
bx ,
bx +
bx *
bx )
x(
x'
bx &
bx %
x$
bx #
0"
bx !
$end
#5000
1"
#10000
0"
#15000
1"
#20000
0"
0(
b0 &
b0 +
b0 %
b0 *
b0 #
b0 )
0'
1$
#25000
b11000110 !
b11000110 ,
1"
#30000
0"
b1 #
b1 )
#35000
b10111101 !
b10111101 ,
1"
#40000
0"
b10 #
b10 )
#45000
b10111010 !
b10111010 ,
1"
#50000
0"
b1001010111111111110 #
b1001010111111111110 )
#55000
b11111000 !
b11111000 ,
1"
#60000
0"
b1001010111111111111 #
b1001010111111111111 )
#65000
1"
#70000
b1001011000000000000 -
b10000000000000000000000000000011 .
0"
1(
