src/dram_ori.v
module dram_ori (
  // inputs
  input clk,
  input ren,
  input wen,
  input [18:0] raddr,
  input [18:0] waddr,
  input [7:0] wdata,
  // input writefile,  // comment out later
  
  // outputs
  output reg [391:0] rdata
);

parameter D_WIDTH =  8;
parameter A_WIDTH =  19;
parameter A_DEPTH = (1 << A_WIDTH);

integer i;
reg [D_WIDTH - 1:0] memory [0:A_DEPTH - 1];

integer out;

always @(posedge clk) begin
  if (ren)
    rdata <= {memory[raddr], memory[raddr+20'd1], memory[raddr+20'd2], memory[raddr+20'd3], memory[raddr+20'd4], memory[raddr+20'd5], memory[raddr+20'd6],
              memory[raddr+20'd640], memory[raddr+20'd641], memory[raddr+20'd642], memory[raddr+20'd643], memory[raddr+20'd644], memory[raddr+20'd645], memory[raddr+20'd646],
              memory[raddr+20'd1280], memory[raddr+20'd1281], memory[raddr+20'd1282], memory[raddr+20'd1283], memory[raddr+20'd1284], memory[raddr+20'd1285], memory[raddr+20'd1286],
              memory[raddr+20'd1920], memory[raddr+20'd1921], memory[raddr+20'd1922], memory[raddr+20'd1923], memory[raddr+20'd1924], memory[raddr+20'd1925], memory[raddr+20'd1926],
              memory[raddr+20'd2560], memory[raddr+20'd2561], memory[raddr+20'd2562], memory[raddr+20'd2563], memory[raddr+20'd2564], memory[raddr+20'd2565], memory[raddr+20'd2566],
              memory[raddr+20'd3200], memory[raddr+20'd3201], memory[raddr+20'd3202], memory[raddr+20'd3203], memory[raddr+20'd3204], memory[raddr+20'd3205], memory[raddr+20'd3206],
              memory[raddr+20'd3840], memory[raddr+20'd3841], memory[raddr+20'd3842], memory[raddr+20'd3843], memory[raddr+20'd3844], memory[raddr+20'd3845], memory[raddr+20'd3846]
    };
  if (wen)
    memory[waddr] <= wdata;
end

// comment out this block later
/*always @(posedge writefile) begin
  out = $fopen("out.txt","w");
  for (i=0; i<307200; i=i+1)
    $fwrite(out,"%h\n",memory[i]);
  $fclose(out);
end*/

initial
begin
  for(i = 0; i < A_DEPTH; i = i + 1)
    memory[i] = 0;
  $readmemh("../../figures/bf/img1.txt", memory, 0, 307199);
  end

endmodule

test/dram_ori_tb.v
`timescale 1 ns/ 1 ps
module dram_ori_tb();
reg clk, ren, wen;
reg [18:0] raddr;
reg [18:0] waddr;
reg [7:0] wdata;
wire [391:0] rdata;
//reg writefile;

dram_ori dr(clk, ren, wen, raddr, waddr, wdata, rdata);

initial begin
	clk = 1'b0;
	repeat (1000) clk = #5 ~clk;
end

initial
  begin
    $dumpfile("dram_ori_tb.vcd");
    $dumpvars(0, dram_ori_tb);
    #20
    // test 1
    ren = 1'b1;
    wen = 1'b0;
    raddr = 20'b0;
    waddr = 20'b0;
    wdata = 8'b0;
    //writefile = 1'b0;
    #10
    // test 2
    ren = 1'b1;
    wen = 1'b0;
    raddr = 20'b1;
    waddr = 20'b0;
    wdata = 8'b0;
    #10
    // test 3
    ren = 1'b1;
    wen = 1'b0;
    raddr = 20'b10;
    waddr = 20'b0;
    wdata = 8'b0;
    #10
    // test 4
    ren = 1'b1;
    wen = 1'b0;
    raddr = 20'b1001010111111111110;
    waddr = 20'b0;
    wdata = 8'b0;
    #10
    // test 5
    ren = 1'b1;
    wen = 1'b0;
    raddr = 20'b1001010111111111111;
    waddr = 20'b0;
    wdata = 8'b0;
    #10
    
    //writefile = 1'b1;
    #20
    $finish;
  end
  
endmodule

test/result/dram_ori_tb.vcd
$date
	Sun May 22 21:19:11 2022
$end
$version
	Icarus Verilog
$end
$timescale
	1ps
$end
$scope module dram_ori_tb $end
$var wire 392 ! rdata [391:0] $end
$var reg 1 " clk $end
$var reg 19 # raddr [18:0] $end
$var reg 1 $ ren $end
$var reg 19 % waddr [18:0] $end
$var reg 8 & wdata [7:0] $end
$var reg 1 ' wen $end
$scope module dr $end
$var wire 1 " clk $end
$var wire 19 ( raddr [18:0] $end
$var wire 1 $ ren $end
$var wire 19 ) waddr [18:0] $end
$var wire 8 * wdata [7:0] $end
$var wire 1 ' wen $end
$var reg 392 + rdata [391:0] $end
$var integer 32 , i [31:0] $end
$upscope $end
$upscope $end
$enddefinitions $end
#0
$dumpvars
b10000000000000000000 ,
bx +
bx *
bx )
bx (
x'
bx &
bx %
x$
bx #
0"
bx !
$end
#5000
1"
#10000
0"
#15000
1"
#20000
0"
b0 &
b0 *
b0 %
b0 )
b0 #
b0 (
0'
1$
#25000
b11000110101111011011101010110011101000111001111010011110101111111011110011000010110000101011010110101101101001111100000010111110110010001100110011000010101110111011010011001000110000101100011011001000110000001011111110111110110010111100001111000100110001001011110110111101101111001100011111000001110001011100100011000001101111011011011011001000110000101100100011001100110001011011111110110101 !
b11000110101111011011101010110011101000111001111010011110101111111011110011000010110000101011010110101101101001111100000010111110110010001100110011000010101110111011010011001000110000101100011011001000110000001011111110111110110010111100001111000100110001001011110110111101101111001100011111000001110001011100100011000001101111011011011011001000110000101100100011001100110001011011111110110101 +
1"
#30000
0"
b1 #
b1 (
#35000
b10111101101110101011001110100011100111101001111010011000101111001100001011000010101101011010110110100111100111001011111011001000110011001100001010111011101101001010100011000010110001101100100011000000101111111011111010110100110000111100010011000100101111011011110110111100101100111100000111000101110010001100000110111101101101101010100111000010110010001100110011000101101111111011010110100101 !
b10111101101110101011001110100011100111101001111010011000101111001100001011000010101101011010110110100111100111001011111011001000110011001100001010111011101101001010100011000010110001101100100011000000101111111011111010110100110000111100010011000100101111011011110110111100101100111100000111000101110010001100000110111101101101101010100111000010110010001100110011000101101111111011010110100101 +
1"
#40000
0"
b10 #
b10 (
#45000
b10111010101100111010001110011110100111101001100010001000110000101100001010110101101011011010011110011100100100011100100011001100110000101011101110110100101010001001110111000110110010001100000010111111101111101011010010100011110001001100010010111101101111011011110010110011101000001100010111001000110000011011110110110110101010011001111111001000110011001100010110111111101101011010010110101001 !
b10111010101100111010001110011110100111101001100010001000110000101100001010110101101011011010011110011100100100011100100011001100110000101011101110110100101010001001110111000110110010001100000010111111101111101011010010100011110001001100010010111101101111011011110010110011101000001100010111001000110000011011110110110110101010011001111111001000110011001100010110111111101101011010010110101001 +
1"
#50000
0"
b1001010111111111110 #
b1001010111111111110 (
#55000
b11111000111110000000000000000000000000000000000000000000000000000000000000000000000000000000000000000000000000000000000000000000000000000000000000000000000000000000000000000000000000000000000000000000000000000000000000000000000000000000000000000000000000000000000000000000000000000000000000000000000000000000000000000000000000000000000000000000000000000000000000000000000000000000000000000000 !
b11111000111110000000000000000000000000000000000000000000000000000000000000000000000000000000000000000000000000000000000000000000000000000000000000000000000000000000000000000000000000000000000000000000000000000000000000000000000000000000000000000000000000000000000000000000000000000000000000000000000000000000000000000000000000000000000000000000000000000000000000000000000000000000000000000000 +
1"
#60000
0"
b1001010111111111111 #
b1001010111111111111 (
#65000
b11111000000000000000000000000000000000000000000000000000000000000000000000000000000000000000000000000000000000000000000000000000000000000000000000000000000000000000000000000000000000000000000000000000000000000000000000000000000000000000000000000000000000000000000000000000000000000000000000000000000000000000000000000000000000000000000000000000000000000000000000000000000000000000000000000000 !
b11111000000000000000000000000000000000000000000000000000000000000000000000000000000000000000000000000000000000000000000000000000000000000000000000000000000000000000000000000000000000000000000000000000000000000000000000000000000000000000000000000000000000000000000000000000000000000000000000000000000000000000000000000000000000000000000000000000000000000000000000000000000000000000000000000000 +
1"
