src/gaussian_core.v
module gaussian_core (
  clk,
  input_pixels,
  result
);

// parameters
parameter BITS = 8;
parameter WIDTH = 7;

// inputs
input clk;
input [391:0] input_pixels;
// outputs
output reg [7:0] result;

// Declare the gaussian mask
integer M[0:WIDTH-1][0:WIDTH-1];

// internal variables
reg [BITS-1:0] A [0:WIDTH-1][0:WIDTH-1];
integer i,j;
integer sum;

always@(*)
  begin
    {M[0][0],M[0][1],M[0][2],M[0][3],M[0][4],M[0][5],M[0][6],
     M[1][0],M[1][1],M[1][2],M[1][3],M[1][4],M[1][5],M[1][6],
     M[2][0],M[2][1],M[2][2],M[2][3],M[2][4],M[2][5],M[2][6],
     M[3][0],M[3][1],M[3][2],M[3][3],M[3][4],M[3][5],M[3][6],
     M[4][0],M[4][1],M[4][2],M[4][3],M[4][4],M[4][5],M[4][6],
     M[5][0],M[5][1],M[5][2],M[5][3],M[5][4],M[5][5],M[5][6],
     M[6][0],M[6][1],M[6][2],M[6][3],M[6][4],M[6][5],M[6][6]} 
     = {32'd5, 32'd9, 32'd14, 32'd16, 32'd14, 32'd9, 32'd5,
        32'd9, 32'd18, 32'd26, 32'd29, 32'd26, 32'd18, 32'd9,
        32'd14, 32'd26, 32'd37, 32'd42, 32'd37, 32'd26, 32'd14,
        32'd16, 32'd29, 32'd42, 32'd48, 32'd42, 32'd29, 32'd16,
        32'd14, 32'd26, 32'd37, 32'd42, 32'd37, 32'd26, 32'd14,
        32'd9, 32'd18, 32'd26, 32'd29, 32'd26, 32'd18, 32'd9,
        32'd5, 32'd9, 32'd14, 32'd16, 32'd14, 32'd9, 32'd5};
     
    {A[0][0],A[0][1],A[0][2],A[0][3],A[0][4],A[0][5],A[0][6],
     A[1][0],A[1][1],A[1][2],A[1][3],A[1][4],A[1][5],A[1][6],
     A[2][0],A[2][1],A[2][2],A[2][3],A[2][4],A[2][5],A[2][6],
     A[3][0],A[3][1],A[3][2],A[3][3],A[3][4],A[3][5],A[3][6],
     A[4][0],A[4][1],A[4][2],A[4][3],A[4][4],A[4][5],A[4][6],
     A[5][0],A[5][1],A[5][2],A[5][3],A[5][4],A[5][5],A[5][6],
     A[6][0],A[6][1],A[6][2],A[6][3],A[6][4],A[6][5],A[6][6]} = input_pixels;
    
    sum = 0;
    for (i=0; i<WIDTH; i++) begin
      for (j=0; j<WIDTH; j++) begin
        sum += A[i][j] * M[i][j];
       end
     end
     result = (sum >> 10);  // result = sum/(2^10)  
  
  end
endmodule

test/gaussian_core_tb.v
`timescale 1 ns/ 1 ps
module gaussian_core_tb();
reg clk;
reg [391:0] input_pixels;
wire [7:0] output_pixel;

gaussian_core gc (clk, input_pixels, output_pixel);

initial begin
	clk = 1'b0;
	repeat (1000) clk = #5 ~clk;
end

initial
  begin
    $dumpfile("gaussian_core_tb.vcd");
    $dumpvars(0, gaussian_core_tb);
    // test 1
    input_pixels = {{13{8'b11111111}}, {13{8'b11001111}},{23{8'b11111101}}};
    #10
    // test 2
    input_pixels = {{44{8'b00000001}},{5{8'b00000001}}};
    #10
    // test 3
    input_pixels = {{13{8'b11100011}}, {13{8'b10001111}},{23{8'b00011101}}};
    #20
    $finish;
  end
  
endmodule

test/result/gaussian_core_tb.vcd
$date
	Mon May 23 21:06:53 2022
$end
$version
	Icarus Verilog
$end
$timescale
	1ps
$end
$scope module gaussian_core_tb $end
$var wire 8 ! output_pixel [7:0] $end
$var reg 1 " clk $end
$var reg 392 # input_pixels [391:0] $end
$scope module gc $end
$var wire 1 " clk $end
$var wire 392 $ input_pixels [391:0] $end
$var reg 8 % result [7:0] $end
$var integer 32 & i [31:0] $end
$var integer 32 ' j [31:0] $end
$var integer 32 ( sum [31:0] $end
$upscope $end
$upscope $end
$enddefinitions $end
#0
$dumpvars
b111011010011011100 (
b111 '
b111 &
b11101101 %
b11111111111111111111111111111111111111111111111111111111111111111111111111111111111111111111111111111111110011111100111111001111110011111100111111001111110011111100111111001111110011111100111111001111110011111111110111111101111111011111110111111101111111011111110111111101111111011111110111111101111111011111110111111101111111011111110111111101111111011111110111111101111111011111110111111101 $
b11111111111111111111111111111111111111111111111111111111111111111111111111111111111111111111111111111111110011111100111111001111110011111100111111001111110011111100111111001111110011111100111111001111110011111111110111111101111111011111110111111101111111011111110111111101111111011111110111111101111111011111110111111101111111011111110111111101111111011111110111111101111111011111110111111101 #
0"
b11101101 !
$end
#5000
b111 '
b111 &
b111011010011011100 (
1"
#10000
b1 !
b1 %
b111 '
b111 &
b10000000100 (
0"
b1000000010000000100000001000000010000000100000001000000010000000100000001000000010000000100000001000000010000000100000001000000010000000100000001000000010000000100000001000000010000000100000001000000010000000100000001000000010000000100000001000000010000000100000001000000010000000100000001000000010000000100000001000000010000000100000001000000010000000100000001000000010000000100000001 #
b1000000010000000100000001000000010000000100000001000000010000000100000001000000010000000100000001000000010000000100000001000000010000000100000001000000010000000100000001000000010000000100000001000000010000000100000001000000010000000100000001000000010000000100000001000000010000000100000001000000010000000100000001000000010000000100000001000000010000000100000001000000010000000100000001 $
#15000
b111 '
b111 &
b10000000100 (
1"
#20000
b1101101 !
b1101101 %
b111 '
b111 &
b11011011110110100 (
0"
b11100011111000111110001111100011111000111110001111100011111000111110001111100011111000111110001111100011100011111000111110001111100011111000111110001111100011111000111110001111100011111000111110001111100011110001110100011101000111010001110100011101000111010001110100011101000111010001110100011101000111010001110100011101000111010001110100011101000111010001110100011101000111010001110100011101 #
b11100011111000111110001111100011111000111110001111100011111000111110001111100011111000111110001111100011100011111000111110001111100011111000111110001111100011111000111110001111100011111000111110001111100011110001110100011101000111010001110100011101000111010001110100011101000111010001110100011101000111010001110100011101000111010001110100011101000111010001110100011101000111010001110100011101 $
#25000
b111 '
b111 &
b11011011110110100 (
1"
#30000
b111 '
b111 &
b11011011110110100 (
0"
#35000
b111 '
b111 &
b11011011110110100 (
1"
#40000
b111 '
b111 &
b11011011110110100 (
0"
