src/gaussian_core.v
module gaussian_core (
  // inputs
  input [391:0] input_pixels,
  // outputs
  output reg [7:0] result
);


parameter BITS = 8;
parameter WIDTH = 7;
// Declare the gaussian mask
integer M[0:WIDTH-1][0:WIDTH-1];

// internal variables
reg [BITS-1:0] A [0:WIDTH-1][0:WIDTH-1];
integer i,j;
integer sum;


always@(input_pixels)
  begin
    {M[0][0],M[0][1],M[0][2],M[0][3],M[0][4],M[0][5],M[0][6],
     M[1][0],M[1][1],M[1][2],M[1][3],M[1][4],M[1][5],M[1][6],
     M[2][0],M[2][1],M[2][2],M[2][3],M[2][4],M[2][5],M[2][6],
     M[3][0],M[3][1],M[3][2],M[3][3],M[3][4],M[3][5],M[3][6],
     M[4][0],M[4][1],M[4][2],M[4][3],M[4][4],M[4][5],M[4][6],
     M[5][0],M[5][1],M[5][2],M[5][3],M[5][4],M[5][5],M[5][6],
     M[6][0],M[6][1],M[6][2],M[6][3],M[6][4],M[6][5],M[6][6]} 
     = {32'd5, 32'd9, 32'd14, 32'd16, 32'd14, 32'd9, 32'd5,
        32'd9, 32'd18, 32'd26, 32'd29, 32'd26, 32'd18, 32'd9,
        32'd14, 32'd26, 32'd37, 32'd42, 32'd37, 32'd26, 32'd14,
        32'd16, 32'd29, 32'd42, 32'd48, 32'd42, 32'd29, 32'd16,
        32'd14, 32'd26, 32'd37, 32'd42, 32'd37, 32'd26, 32'd14,
        32'd9, 32'd18, 32'd26, 32'd29, 32'd26, 32'd18, 32'd9,
        32'd5, 32'd9, 32'd14, 32'd16, 32'd14, 32'd9, 32'd5};
     
    {A[0][0],A[0][1],A[0][2],A[0][3],A[0][4],A[0][5],A[0][6],
     A[1][0],A[1][1],A[1][2],A[1][3],A[1][4],A[1][5],A[1][6],
     A[2][0],A[2][1],A[2][2],A[2][3],A[2][4],A[2][5],A[2][6],
     A[3][0],A[3][1],A[3][2],A[3][3],A[3][4],A[3][5],A[3][6],
     A[4][0],A[4][1],A[4][2],A[4][3],A[4][4],A[4][5],A[4][6],
     A[5][0],A[5][1],A[5][2],A[5][3],A[5][4],A[5][5],A[5][6],
     A[6][0],A[6][1],A[6][2],A[6][3],A[6][4],A[6][5],A[6][6]} = input_pixels;
     //$display(M[0][0]);
     //$display(A[0][0]);
    
    sum = 0;
    for (i=0; i<WIDTH; i++) begin
      for (j=0; j<WIDTH; j++) begin
        sum += A[i][j] * M[i][j];
        //$display(sum);
       end
     end
     result = (sum >> 10);  // result = sum/(2^10)  
  
  end
endmodule

src/dram.v
// This is DRAM 2 which stores the filtered image
module dram (
  clk,
  ren,
  wen,
  raddr,
  waddr,
  wdata,
  writefile,  // signal showing the gaussian part is done
  rdata
);

// parameters
parameter D_WIDTH = 8;
parameter A_WIDTH = 21;
parameter A_DEPTH = (1 << A_WIDTH);
parameter PATCHLEN = 961*8;

// inputs
input clk;
input ren;
input wen;
input [A_WIDTH-1:0] raddr;
input [A_WIDTH-1:0] waddr;
input [D_WIDTH-1:0] wdata;
input writefile;  // comment out later
// outputs
output reg [PATCHLEN-1:0] rdata;

// internal variables
integer i;
reg [D_WIDTH-1:0] memory [0:A_DEPTH-1];
integer out;
wire [247:0] patch [0:30];

// modify this part later
genvar j;
generate
  for (j=0; j<31; j=j+1) begin
    assign patch[j] = {memory[raddr+(j-15)*1280-15],memory[raddr+(j-15)*1280-14],memory[raddr+(j-15)*1280-13],memory[raddr+(j-15)*1280-12],
                       memory[raddr+(j-15)*1280-11],memory[raddr+(j-15)*1280-10],memory[raddr+(j-15)*1280- 9],memory[raddr+(j-15)*1280- 8],
                       memory[raddr+(j-15)*1280- 7],memory[raddr+(j-15)*1280- 6],memory[raddr+(j-15)*1280- 5],memory[raddr+(j-15)*1280- 4],
                       memory[raddr+(j-15)*1280- 3],memory[raddr+(j-15)*1280- 2],memory[raddr+(j-15)*1280- 1],memory[raddr+(j-15)*1280   ],
                       memory[raddr+(j-15)*1280+ 1],memory[raddr+(j-15)*1280+ 2],memory[raddr+(j-15)*1280+ 3],memory[raddr+(j-15)*1280+ 4],
                       memory[raddr+(j-15)*1280+ 5],memory[raddr+(j-15)*1280+ 6],memory[raddr+(j-15)*1280+ 7],memory[raddr+(j-15)*1280+ 8],
                       memory[raddr+(j-15)*1280+ 9],memory[raddr+(j-15)*1280+10],memory[raddr+(j-15)*1280+11],memory[raddr+(j-15)*1280+12],
                       memory[raddr+(j-15)*1280+13],memory[raddr+(j-15)*1280+14],memory[raddr+(j-15)*1280+15]};
  end
endgenerate


always @(posedge clk) begin
  if (ren) begin
    rdata <= {patch[0], patch[1], patch[2], patch[3], patch[4], patch[5], patch[6], patch[7],
              patch[8], patch[9], patch[10],patch[11],patch[12],patch[13],patch[14],patch[15],
              patch[16],patch[17],patch[18],patch[19],patch[20],patch[21],patch[22],patch[23],
              patch[24],patch[25],patch[26],patch[27],patch[28],patch[29],patch[30]};
  end
  else if (wen) begin
    memory[waddr] <= wdata;
  end
  else begin
    rdata <= {PATCHLEN{1'b0}};
  end
end

/*
// this is just for testing (priting out the memory), comment out later
always @(posedge writefile) begin
  out = $fopen("filtered/out22.txt","w");
  for (i=0; i<921600; i=i+1)
    $fwrite(out,"%h\n",memory[i]);
  $fclose(out);
end
*/

initial begin
  for(i = 0; i < A_DEPTH; i = i + 1)
    memory[i] = 8'hff;
end

endmodule

src/dram_ori.v
module dram_ori (
  clk,
  ren,
  wen,
  raddr,
  waddr,
  wdata,
  rdata
);

// parameters
parameter D_WIDTH = 8;
parameter A_WIDTH = 21;
parameter A_DEPTH = (1 << A_WIDTH);
parameter MASKLEN = 392;

// inputs
input clk;
input ren;
input wen;
input [A_WIDTH-1:0] raddr;
input [A_WIDTH-1:0] waddr;
input [D_WIDTH-1:0] wdata;
// outputs
output reg [MASKLEN-1:0] rdata;

// internal variables
integer i;
reg [D_WIDTH-1:0] memory [0:A_DEPTH-1];

always @(posedge clk) begin
  if (ren) begin
    rdata <= {memory[raddr], memory[raddr+1], memory[raddr+2], memory[raddr+3], memory[raddr+4], memory[raddr+5], memory[raddr+6],
              //memory[raddr+640], memory[raddr+641], memory[raddr+642], memory[raddr+643], memory[raddr+644], memory[raddr+645], memory[raddr+646],
              memory[raddr+1280], memory[raddr+1281], memory[raddr+1282], memory[raddr+1283], memory[raddr+1284], memory[raddr+1285], memory[raddr+1286],
              //memory[raddr+1920], memory[raddr+1921], memory[raddr+1922], memory[raddr+1923], memory[raddr+1924], memory[raddr+1925], memory[raddr+20'd1926],
              memory[raddr+2560], memory[raddr+2561], memory[raddr+2562], memory[raddr+2563], memory[raddr+2564], memory[raddr+2565], memory[raddr+20'd2566],
              //memory[raddr+3200], memory[raddr+3201], memory[raddr+3202], memory[raddr+3203], memory[raddr+3204], memory[raddr+3205], memory[raddr+20'd3206],
              memory[raddr+3840], memory[raddr+3841], memory[raddr+3842], memory[raddr+3843], memory[raddr+3844], memory[raddr+3845], memory[raddr+3846],
              memory[raddr+5120], memory[raddr+5121], memory[raddr+5122], memory[raddr+5123], memory[raddr+5124], memory[raddr+5125], memory[raddr+5126],
              memory[raddr+6400], memory[raddr+6401], memory[raddr+6402], memory[raddr+6403], memory[raddr+6404], memory[raddr+6405], memory[raddr+6406],
              memory[raddr+7680], memory[raddr+7681], memory[raddr+7682], memory[raddr+7683], memory[raddr+7684], memory[raddr+7685], memory[raddr+7686]};
  end
  else if (wen) begin
    memory[waddr] <= wdata;
  end
  else begin
    rdata <= {392{1'b0}};
  end
end

initial begin
  for(i = 0; i < A_DEPTH; i = i + 1)
    memory[i] = 8'hff;
  $readmemh("../../figures/bf/img1.txt", memory, 0, 921599);
end

endmodule

src/gaussian_ctrl.v
module gaussian_ctrl (
  // inputs
  input clk,
  input rst,
  // outputs
  output reg done
);

reg ren1, wen1, ren2, wen2;
reg [18:0] raddr;
reg [18:0] waddr;
//reg [7:0] wdata1, wdata2;
wire [7:0] output_pixel;
wire [391:0] rdata1, rdata2;
reg [391:0] input_pixels;
reg writefile; //comment out later

parameter BITS = 8;
parameter WIDTH = 7;
parameter ROW = 480;
parameter COL = 640;
integer i = 0;
integer j = 0;
            
dram_ori dr(clk, ren1, wen1, raddr, 19'hxxx, 8'hx, rdata1);
dram buffer(clk, ren2, wen2, 19'hxxx, waddr, output_pixel, writefile, rdata2);

gaussian_core gc (.input_pixels(input_pixels), .result(output_pixel));

always @(posedge clk) begin
  //writefile = 1'b0;
  if (i < ROW - 6) begin
    if (j < COL - 6) begin
      ren1 = 1'b1;
      ren2 = 1'b0;
      wen1 = 1'b0;
      wen2 = 1'b1;
      raddr = 19'd640 * i + j;
      waddr = 19'd640 * (i+1) + (j+1);
      input_pixels = rdata1;
      j = j + 1;
    end else begin
      i = i + 1;
      j = 0;
    end
  end else begin
    ren1 = 1'b0;
    ren2 = 1'b0;
    wen1 = 1'b0;
    wen2 = 1'b0;
    writefile = 1'b1;
  end
end

always @(posedge clk) begin
  done <= 1'b0;
  if (writefile)
      done <= 1'b1;
end
  
endmodule

test/gaussian_ctrl_tb.v
`timescale 1 ns/ 1 ps
module gaussian_ctrl_tb();
reg clk, rst;
wire done;

gaussian_ctrl gctrl (clk, rst, done);

initial begin
	clk = 1'b0;
	repeat (1000000) clk = #2 ~clk;
end

initial
  begin
    $dumpfile("gaussian_ctrl_tb.vcd");
    $dumpvars(0, gaussian_ctrl_tb);
    // test 1
    rst = 1'b1;
    #10
    // test 2
    rst = 1'b0;
    // test 3
    //#1300000
    #2000
    $finish ; // This causes the simulation to end.  Without, it would go on..and on.
  end
  
endmodule

test/result/gaussian_ctrl_tb.vcd
$date
	Mon May 23 13:33:53 2022
$end
$version
	Icarus Verilog
$end
$timescale
	1ps
$end
$scope module gaussian_ctrl_tb $end
$var wire 1 ! done $end
$var reg 1 " clk $end
$var reg 1 # rst $end
$scope module gctrl $end
$var wire 1 " clk $end
$var wire 1 # rst $end
$var wire 392 $ rdata2 [391:0] $end
$var wire 392 % rdata1 [391:0] $end
$var wire 8 & output_pixel [7:0] $end
$var reg 1 ! done $end
$var reg 392 ' input_pixels [391:0] $end
$var reg 19 ( raddr [18:0] $end
$var reg 1 ) ren1 $end
$var reg 1 * ren2 $end
$var reg 19 + waddr [18:0] $end
$var reg 1 , wen1 $end
$var reg 1 - wen2 $end
$var reg 1 . writefile $end
$var integer 32 / i [31:0] $end
$var integer 32 0 j [31:0] $end
$scope module buffer $end
$var wire 1 " clk $end
$var wire 19 1 raddr [18:0] $end
$var wire 1 * ren $end
$var wire 19 2 waddr [18:0] $end
$var wire 1 - wen $end
$var wire 1 . writefile $end
$var wire 8 3 wdata [7:0] $end
$var reg 392 4 rdata [391:0] $end
$var integer 32 5 i [31:0] $end
$var integer 32 6 out [31:0] $end
$upscope $end
$scope module dr $end
$var wire 1 " clk $end
$var wire 19 7 raddr [18:0] $end
$var wire 1 ) ren $end
$var wire 19 8 waddr [18:0] $end
$var wire 8 9 wdata [7:0] $end
$var wire 1 , wen $end
$var reg 392 : rdata [391:0] $end
$var integer 32 ; i [31:0] $end
$upscope $end
$scope module gc $end
$var wire 392 < input_pixels [391:0] $end
$var reg 8 = result [7:0] $end
$var integer 32 > i [31:0] $end
$var integer 32 ? j [31:0] $end
$var integer 32 @ sum [31:0] $end
$upscope $end
$upscope $end
$upscope $end
$enddefinitions $end
#0
$dumpvars
bx @
bx ?
bx >
bx =
bx <
b10000000000000000000 ;
bx :
bx 9
bx 8
bx 7
bx 6
b10000000000000000000 5
bx 4
bx 3
bx 2
bx 1
b0 0
b0 /
x.
x-
x,
bx +
x*
x)
bx (
bx '
bx &
bx %
bx $
1#
0"
x!
$end
#2000
b11000110101111011011101010110011101000111001111010011110101111111011110011000010110000101011010110101101101001111100000010111110110010001100110011000010101110111011010011001000110000101100011011001000110000001011111110111110110010111100001111000100110001001011110110111101101111001100011111000001110001011100100011000001101111011011011011001000110000101100100011001100110001011011111110110101 %
b11000110101111011011101010110011101000111001111010011110101111111011110011000010110000101011010110101101101001111100000010111110110010001100110011000010101110111011010011001000110000101100011011001000110000001011111110111110110010111100001111000100110001001011110110111101101111001100011111000001110001011100100011000001101111011011011011001000110000101100100011001100110001011011111110110101 :
0!
b1 0
b1010000001 +
b1010000001 2
b0 (
b0 7
1-
0,
0*
1)
1"
#4000
0"
#6000
b11000001 &
b11000001 3
b11000001 =
b111 ?
b111 >
b110000010000011110 @
b10 0
b11000110101111011011101010110011101000111001111010011110101111111011110011000010110000101011010110101101101001111100000010111110110010001100110011000010101110111011010011001000110000101100011011001000110000001011111110111110110010111100001111000100110001001011110110111101101111001100011111000001110001011100100011000001101111011011011011001000110000101100100011001100110001011011111110110101 '
b11000110101111011011101010110011101000111001111010011110101111111011110011000010110000101011010110101101101001111100000010111110110010001100110011000010101110111011010011001000110000101100011011001000110000001011111110111110110010111100001111000100110001001011110110111101101111001100011111000001110001011100100011000001101111011011011011001000110000101100100011001100110001011011111110110101 <
b1010000010 +
b1010000010 2
b1 (
b1 7
1"
#8000
0"
#10000
b10111010101100111010001110011110100111101001100010001000110000101100001010110101101011011010011110011100100100011100100011001100110000101011101110110100101010001001110111000110110010001100000010111111101111101011010010100011110001001100010010111101101111011011110010110011101000001100010111001000110000011011110110110110101010011001111111001000110011001100010110111111101101011010010110101001 %
b10111010101100111010001110011110100111101001100010001000110000101100001010110101101011011010011110011100100100011100100011001100110000101011101110110100101010001001110111000110110010001100000010111111101111101011010010100011110001001100010010111101101111011011110010110011101000001100010111001000110000011011110110110110101010011001111111001000110011001100010110111111101101011010010110101001 :
b11 0
b1010000011 +
b1010000011 2
b10 (
b10 7
1"
0#
#12000
0"
#14000
b10111000 &
b10111000 3
b10111000 =
b111 ?
b111 >
b101110000011000001 @
b100 0
b10111010101100111010001110011110100111101001100010001000110000101100001010110101101011011010011110011100100100011100100011001100110000101011101110110100101010001001110111000110110010001100000010111111101111101011010010100011110001001100010010111101101111011011110010110011101000001100010111001000110000011011110110110110101010011001111111001000110011001100010110111111101101011010010110101001 '
b10111010101100111010001110011110100111101001100010001000110000101100001010110101101011011010011110011100100100011100100011001100110000101011101110110100101010001001110111000110110010001100000010111111101111101011010010100011110001001100010010111101101111011011110010110011101000001100010111001000110000011011110110110110101010011001111111001000110011001100010110111111101101011010010110101001 <
b1010000100 +
b1010000100 2
b11 (
b11 7
1"
#16000
0"
#18000
b10100011100111101001111010011000100010001000001101110010101101011010110110100111100111001001000110001010011101001100001010111011101101001010100010011101100100110111100011000000101111111011111010110100101000111001100001111011101111011011110110111100101100111010000010010110011110101100000110111101101101101010100110011111100101000111100011000101101111111011010110100101101010011001101101111011 %
b10100011100111101001111010011000100010001000001101110010101101011010110110100111100111001001000110001010011101001100001010111011101101001010100010011101100100110111100011000000101111111011111010110100101000111001100001111011101111011011110110111100101100111010000010010110011110101100000110111101101101101010100110011111100101000111100011000101101111111011010110100101101010011001101101111011 :
b101 0
b1010000101 +
b1010000101 2
b100 (
b100 7
1"
#20000
0"
#22000
b10100110 &
b10100110 3
b10100110 =
b111 ?
b111 >
b101001101111010101 @
b110 0
b10100011100111101001111010011000100010001000001101110010101101011010110110100111100111001001000110001010011101001100001010111011101101001010100010011101100100110111100011000000101111111011111010110100101000111001100001111011101111011011110110111100101100111010000010010110011110101100000110111101101101101010100110011111100101000111100011000101101111111011010110100101101010011001101101111011 '
b10100011100111101001111010011000100010001000001101110010101101011010110110100111100111001001000110001010011101001100001010111011101101001010100010011101100100110111100011000000101111111011111010110100101000111001100001111011101111011011110110111100101100111010000010010110011110101100000110111101101101101010100110011111100101000111100011000101101111111011010110100101101010011001101101111011 <
b1010000110 +
b1010000110 2
b101 (
b101 7
1"
#24000
0"
#26000
b10011110100110001000100010000011011100100111010101110010101001111001110010010001100010100111010001110010011011011011010010101000100111011001001101111000011100010110100110111110101101001010001110011000011110110111001101101010101111001011001110100000100101100111101001110011011010101011011010101001100111111001010001111000011100000110011110110101101001011010100110011011011110110110111101100100 %
b10011110100110001000100010000011011100100111010101110010101001111001110010010001100010100111010001110010011011011011010010101000100111011001001101111000011100010110100110111110101101001010001110011000011110110111001101101010101111001011001110100000100101100111101001110011011010101011011010101001100111111001010001111000011100000110011110110101101001011010100110011011011110110110111101100100 :
b111 0
b1010000111 +
b1010000111 2
b110 (
b110 7
1"
#28000
0"
#30000
b10001110 &
b10001110 3
b10001110 =
b111 ?
b111 >
b100011101000011011 @
b1000 0
b10011110100110001000100010000011011100100111010101110010101001111001110010010001100010100111010001110010011011011011010010101000100111011001001101111000011100010110100110111110101101001010001110011000011110110111001101101010101111001011001110100000100101100111101001110011011010101011011010101001100111111001010001111000011100000110011110110101101001011010100110011011011110110110111101100100 '
b10011110100110001000100010000011011100100111010101110010101001111001110010010001100010100111010001110010011011011011010010101000100111011001001101111000011100010110100110111110101101001010001110011000011110110111001101101010101111001011001110100000100101100111101001110011011010101011011010101001100111111001010001111000011100000110011110110101101001011010100110011011011110110110111101100100 <
b1010001000 +
b1010001000 2
b111 (
b111 7
1"
#32000
0"
#34000
b10001000100000110111001001110101011100100110100001101101100100011000101001110100011100100110110101100010011010001001110110010011011110000111000101101001010111010110010010100011100110000111101101110011011010100101110101100100101000001001011001111010011100110110101001011101011001001001111110010100011110000111000001100111010110100110000110101001100110110111101101101111011001000101011101011111 %
b10001000100000110111001001110101011100100110100001101101100100011000101001110100011100100110110101100010011010001001110110010011011110000111000101101001010111010110010010100011100110000111101101110011011010100101110101100100101000001001011001111010011100110110101001011101011001001001111110010100011110000111000001100111010110100110000110101001100110110111101101101111011001000101011101011111 :
b1001 0
b1010001001 +
b1010001001 2
b1000 (
b1000 7
1"
#36000
0"
#38000
b1110101 &
b1110101 3
b1110101 =
b111 ?
b111 >
b11101011101010111 @
b1010 0
b10001000100000110111001001110101011100100110100001101101100100011000101001110100011100100110110101100010011010001001110110010011011110000111000101101001010111010110010010100011100110000111101101110011011010100101110101100100101000001001011001111010011100110110101001011101011001001001111110010100011110000111000001100111010110100110000110101001100110110111101101101111011001000101011101011111 '
b10001000100000110111001001110101011100100110100001101101100100011000101001110100011100100110110101100010011010001001110110010011011110000111000101101001010111010110010010100011100110000111101101110011011010100101110101100100101000001001011001111010011100110110101001011101011001001001111110010100011110000111000001100111010110100110000110101001100110110111101101101111011001000101011101011111 <
b1010001010 +
b1010001010 2
b1001 (
b1001 7
1"
#40000
0"
#42000
b1110010011101010111001001101000011011010110011101100011011101000111001001101101011000100110100001100011011001110111100001110001011010010101110101100100011000000110000101111011011100110110101001011101011001000110000001011010011110100111001101101010010111010110010001011111010110100111100001110000011001110101101001100001010111000101101001111011011011110110010001010111010111110101110001011001 %
b1110010011101010111001001101000011011010110011101100011011101000111001001101101011000100110100001100011011001110111100001110001011010010101110101100100011000000110000101111011011100110110101001011101011001000110000001011010011110100111001101101010010111010110010001011111010110100111100001110000011001110101101001100001010111000101101001111011011011110110010001010111010111110101110001011001 :
b1011 0
b1010001011 +
b1010001011 2
b1010 (
b1010 7
1"
#44000
0"
#46000
b1100110 &
b1100110 3
b1100110 =
b111 ?
b111 >
b11001100111111111 @
b1100 0
b1110010011101010111001001101000011011010110011101100011011101000111001001101101011000100110100001100011011001110111100001110001011010010101110101100100011000000110000101111011011100110110101001011101011001000110000001011010011110100111001101101010010111010110010001011111010110100111100001110000011001110101101001100001010111000101101001111011011011110110010001010111010111110101110001011001 '
b1110010011101010111001001101000011011010110011101100011011101000111001001101101011000100110100001100011011001110111100001110001011010010101110101100100011000000110000101111011011100110110101001011101011001000110000001011010011110100111001101101010010111010110010001011111010110100111100001110000011001110101101001100001010111000101101001111011011011110110010001010111010111110101110001011001 <
b1010001100 +
b1010001100 2
b1011 (
b1011 7
1"
#48000
0"
#50000
b1110010011010000110110101100111011000110110000101011111011011010110001001101000011000110110011101100101011000110110100101011101011001000110000001100001011000000101111101101010010111010110010001100000010110100101100101011010011010100101110101100100010111110101101001011011010111010110011101011010011000010101110001011010010111000101111101100100010101110101111101011100010110010101101101011110 %
b1110010011010000110110101100111011000110110000101011111011011010110001001101000011000110110011101100101011000110110100101011101011001000110000001100001011000000101111101101010010111010110010001100000010110100101100101011010011010100101110101100100010111110101101001011011010111010110011101011010011000010101110001011010010111000101111101100100010101110101111101011100010110010101101101011110 :
b1101 0
b1010001101 +
b1010001101 2
b1100 (
b1100 7
1"
#52000
0"
#54000
b1100000 &
b1100000 3
b1100000 =
b111 ?
b111 >
b11000001010001100 @
b1110 0
b1110010011010000110110101100111011000110110000101011111011011010110001001101000011000110110011101100101011000110110100101011101011001000110000001100001011000000101111101101010010111010110010001100000010110100101100101011010011010100101110101100100010111110101101001011011010111010110011101011010011000010101110001011010010111000101111101100100010101110101111101011100010110010101101101011110 '
b1110010011010000110110101100111011000110110000101011111011011010110001001101000011000110110011101100101011000110110100101011101011001000110000001100001011000000101111101101010010111010110010001100000010110100101100101011010011010100101110101100100010111110101101001011011010111010110011101011010011000010101110001011010010111000101111101100100010101110101111101011100010110010101101101011110 <
b1010001110 +
b1010001110 2
b1101 (
b1101 7
1"
#56000
0"
#58000
b1101101011001110110001101100001010111110110001001101000011010000110001101100111011001010110001101100101011010100110010001100000011000010110000001011111011000000110010001100100011000000101101001011001010110100101110001011111011001000101111101011010010110110101110101011111011000100110000101011100010110100101110001011111011000010110001001011111010111000101100101011011010111100101111101011101 %
b1101101011001110110001101100001010111110110001001101000011010000110001101100111011001010110001101100101011010100110010001100000011000010110000001011111011000000110010001100100011000000101101001011001010110100101110001011111011001000101111101011010010110110101110101011111011000100110000101011100010110100101110001011111011000010110001001011111010111000101100101011011010111100101111101011101 :
b1111 0
b1010001111 +
b1010001111 2
b1110 (
b1110 7
1"
#60000
0"
#62000
b1011111 &
b1011111 3
b1011111 =
b111 ?
b111 >
b10111110110111110 @
b10000 0
b1101101011001110110001101100001010111110110001001101000011010000110001101100111011001010110001101100101011010100110010001100000011000010110000001011111011000000110010001100100011000000101101001011001010110100101110001011111011001000101111101011010010110110101110101011111011000100110000101011100010110100101110001011111011000010110001001011111010111000101100101011011010111100101111101011101 '
b1101101011001110110001101100001010111110110001001101000011010000110001101100111011001010110001101100101011010100110010001100000011000010110000001011111011000000110010001100100011000000101101001011001010110100101110001011111011001000101111101011010010110110101110101011111011000100110000101011100010110100101110001011111011000010110001001011111010111000101100101011011010111100101111101011101 <
b1010010000 +
b1010010000 2
b1111 (
b1111 7
1"
#64000
0"
#66000
b1100011011000010101111101100010011010000110110101110000011001110110010101100011011001010110101001101111011100010110000101100000010111110110000001100100011010000110100101011010010110010101101001011100010111110110001001100100010110100101101101011101010111110110001001100101011010000101101001011100010111110110000101100010011001000110011001011001010110110101111001011111010111010101110101011111 %
b1100011011000010101111101100010011010000110110101110000011001110110010101100011011001010110101001101111011100010110000101100000010111110110000001100100011010000110100101011010010110010101101001011100010111110110001001100100010110100101101101011101010111110110001001100101011010000101101001011100010111110110000101100010011001000110011001011001010110110101111001011111010111010101110101011111 :
b10001 0
b1010010001 +
b1010010001 2
b10000 (
b10000 7
1"
#68000
0"
#70000
b1100001 &
b1100001 3
b1100001 =
b111 ?
b111 >
b11000010101110100 @
b10010 0
b1100011011000010101111101100010011010000110110101110000011001110110010101100011011001010110101001101111011100010110000101100000010111110110000001100100011010000110100101011010010110010101101001011100010111110110001001100100010110100101101101011101010111110110001001100101011010000101101001011100010111110110000101100010011001000110011001011001010110110101111001011111010111010101110101011111 '
b1100011011000010101111101100010011010000110110101110000011001110110010101100011011001010110101001101111011100010110000101100000010111110110000001100100011010000110100101011010010110010101101001011100010111110110001001100100010110100101101101011101010111110110001001100101011010000101101001011100010111110110000101100010011001000110011001011001010110110101111001011111010111010101110101011111 <
b1010010010 +
b1010010010 2
b10001 (
b10001 7
1"
#72000
0"
#74000
b1011111011000100110100001101101011100000111000001111000011000110110010101101010011011110111000101110001011100010101111101100000011001000110100001101001011010100110111001011010010111000101111101100010011001000110010101101111010111010101111101100010011001010110100001101010011100010101111101100001011000100110010001100110011010010110110101011110010111110101110101011101010111110110000101101000 %
b1011111011000100110100001101101011100000111000001111000011000110110010101101010011011110111000101110001011100010101111101100000011001000110100001101001011010100110111001011010010111000101111101100010011001000110010101101111010111010101111101100010011001010110100001101010011100010101111101100001011000100110010001100110011010010110110101011110010111110101110101011101010111110110000101101000 :
b10011 0
b1010010011 +
b1010010011 2
b10010 (
b10010 7
1"
#76000
0"
#78000
b1100101 &
b1100101 3
b1100101 =
b111 ?
b111 >
b11001011111101000 @
b10100 0
b1011111011000100110100001101101011100000111000001111000011000110110010101101010011011110111000101110001011100010101111101100000011001000110100001101001011010100110111001011010010111000101111101100010011001000110010101101111010111010101111101100010011001010110100001101010011100010101111101100001011000100110010001100110011010010110110101011110010111110101110101011101010111110110000101101000 '
b1011111011000100110100001101101011100000111000001111000011000110110010101101010011011110111000101110001011100010101111101100000011001000110100001101001011010100110111001011010010111000101111101100010011001000110010101101111010111010101111101100010011001010110100001101010011100010101111101100001011000100110010001100110011010010110110101011110010111110101110101011101010111110110000101101000 <
b1010010100 +
b1010010100 2
b10011 (
b10011 7
1"
#80000
0"
#82000
b1101000011011010111000001110000011110000111100101111010011010100110111101110001011100010111000101110011011101010110010001101000011010010110101001101110011011110111000101011111011000100110010001100101011011110111000001110001011000100110010101101000011010100111000101110000011100000110001001100100011001100110100101101101011010110110101001011101010111010101111101100001011010000110010101100100 %
b1101000011011010111000001110000011110000111100101111010011010100110111101110001011100010111000101110011011101010110010001101000011010010110101001101110011011110111000101011111011000100110010001100101011011110111000001110001011000100110010101101000011010100111000101110000011100000110001001100100011001100110100101101101011010110110101001011101010111010101111101100001011010000110010101100100 :
b10101 0
b1010010101 +
b1010010101 2
b10100 (
b10100 7
1"
#84000
0"
#86000
b1101011 &
b1101011 3
b1101011 =
b111 ?
b111 >
b11010110001101100 @
b10110 0
b1101000011011010111000001110000011110000111100101111010011010100110111101110001011100010111000101110011011101010110010001101000011010010110101001101110011011110111000101011111011000100110010001100101011011110111000001110001011000100110010101101000011010100111000101110000011100000110001001100100011001100110100101101101011010110110101001011101010111010101111101100001011010000110010101100100 '
b1101000011011010111000001110000011110000111100101111010011010100110111101110001011100010111000101110011011101010110010001101000011010010110101001101110011011110111000101011111011000100110010001100101011011110111000001110001011000100110010101101000011010100111000101110000011100000110001001100100011001100110100101101101011010110110101001011101010111010101111101100001011010000110010101100100 <
b1010010110 +
b1010010110 2
b10101 (
b10101 7
1"
#88000
0"
#90000
b1110000011100000111100001111001011110100111100101111000011100010111000101110001011100110111010101110101011101100110100101101010011011100110111101110001011100110111010101100100011001010110111101110000011100010111001101110111011010000110101001110001011100000111000001110001011101010110011001101001011011010110101101101010011010110110111101011111011000010110100001100101011001000110010101101010 %
b1110000011100000111100001111001011110100111100101111000011100010111000101110001011100110111010101110101011101100110100101101010011011100110111101110001011100110111010101100100011001010110111101110000011100010111001101110111011010000110101001110001011100000111000001110001011101010110011001101001011011010110101101101010011010110110111101011111011000010110100001100101011001000110010101101010 :
b10111 0
b1010010111 +
b1010010111 2
b10110 (
b10110 7
1"
#92000
0"
#94000
b1101111 &
b1101111 3
b1101111 =
b111 ?
b111 >
b11011110100010000 @
b11000 0
b1110000011100000111100001111001011110100111100101111000011100010111000101110001011100110111010101110101011101100110100101101010011011100110111101110001011100110111010101100100011001010110111101110000011100010111001101110111011010000110101001110001011100000111000001110001011101010110011001101001011011010110101101101010011010110110111101011111011000010110100001100101011001000110010101101010 '
b1110000011100000111100001111001011110100111100101111000011100010111000101110001011100110111010101110101011101100110100101101010011011100110111101110001011100110111010101100100011001010110111101110000011100010111001101110111011010000110101001110001011100000111000001110001011101010110011001101001011011010110101101101010011010110110111101011111011000010110100001100101011001000110010101101010 <
b1010011000 +
b1010011000 2
b10111 (
b10111 7
1"
#96000
0"
#98000
b1111000011110010111101001111001011110000111101001111111011100010111001101110101011101010111011001111001011111100110111001101111011100010111001101110101011110101000000001101111011100000111000101110011011101110111110010000001011100010111000001110000011100010111010101111001011111010110110101101011011010100110101101101111011100110111010101101000011001010110010001100101011010100110111101110001 %
b1111000011110010111101001111001011110000111101001111111011100010111001101110101011101010111011001111001011111100110111001101111011100010111001101110101011110101000000001101111011100000111000101110011011101110111110010000001011100010111000001110000011100010111010101111001011111010110110101101011011010100110101101101111011100110111010101101000011001010110010001100101011010100110111101110001 :
b11001 0
b1010011001 +
b1010011001 2
b11000 (
b11000 7
1"
#100000
0"
#102000
b1110011 &
b1110011 3
b1110011 =
b111 ?
b111 >
b11100110110111011 @
b11010 0
b1111000011110010111101001111001011110000111101001111111011100010111001101110101011101010111011001111001011111100110111001101111011100010111001101110101011110101000000001101111011100000111000101110011011101110111110010000001011100010111000001110000011100010111010101111001011111010110110101101011011010100110101101101111011100110111010101101000011001010110010001100101011010100110111101110001 '
b1111000011110010111101001111001011110000111101001111111011100010111001101110101011101010111011001111001011111100110111001101111011100010111001101110101011110101000000001101111011100000111000101110011011101110111110010000001011100010111000001110000011100010111010101111001011111010110110101101011011010100110101101101111011100110111010101101000011001010110010001100101011010100110111101110001 <
b1010011010 +
b1010011010 2
b11001 (
b11001 7
1"
#104000
0"
#106000
b1111010011110010111100001111010011111111000010010000010011101010111010101110110011110010111111010000011100000110111000101110011011101010111101010000000100001001000000001110001011100110111011101111100100000011000010001111110011100000111000101110101011110010111110101111111100000000110101001101011011011110111001101110101011101101000000001100100011001010110101001101111011100010111000101110110 %
b1111010011110010111100001111010011111111000010010000010011101010111010101110110011110010111111010000011100000110111000101110011011101010111101010000000100001001000000001110001011100110111011101111100100000011000010001111110011100000111000101110101011110010111110101111111100000000110101001101011011011110111001101110101011101101000000001100100011001010110101001101111011100010111000101110110 :
b11011 0
b1010011011 +
b1010011011 2
b11010 (
b11010 7
1"
#108000
0"
